{
  "version": "7",
  "dialect": "sqlite",
  "entries": [
    {
      "idx": 0,
      "version": "6",
      "when": 1782686705075,
      "tag": "0000_opposite_joshua_kane",
      "breakpoints": true
    },
    {
      "idx": 1,
      "version": "6",
      "when": 1782688808954,
      "tag": "0001_smart_sabretooth",
      "breakpoints": true
    },
    {
      "idx": 2,
      "version": "6",
      "when": 1782703208629,
      "tag": "0002_sticky_havok",
      "breakpoints": true
    },
    {
      "idx": 3,
      "version": "6",
      "when": 1782740144557,
      "tag": "0003_stiff_rattler",
      "breakpoints": true
    },
    {
      "idx": 4,
      "version": "6",
      "when": 1782828383265,
      "tag": "0004_left_kinsey_walden",
      "breakpoints": true
    },
    {
      "idx": 5,
      "version": "6",
      "when": 1782934090603,
      "tag": "0005_true_secret_warriors",
      "breakpoints": true
    },
    {
      "idx": 6,
      "version": "6",
      "when": 1783555868646,
      "tag": "0006_rare_fixer",
      "breakpoints": true
    },
    {
      "idx": 7,
      "version": "6",
      "when": 1784131757358,
      "tag": "0007_new_pepper_potts",
      "breakpoints": true
    }
  ]
}
